flowviz/__init__.py
flowviz-0.0.1.dist-info/LICENSE
flowviz-0.0.1.dist-info/WHEEL
flowviz-0.0.1.dist-info/METADATA
flowviz-0.0.1.dist-info/RECORD
